koicore/__init__.py
koicore/koi_object.py
koicore/enums/__init__.py
koicore/enums/visibility.py
koicore/other/__init__.py
koicore/other/koi_variable.py
koicore/types/__init__.py
koicore/types/koi_boolean.py
koicore/types/koi_character.py
koicore/types/koi_integer.py
koicore/types/koi_string.py
koicore-1.2.0.dist-info/DESCRIPTION.rst
koicore-1.2.0.dist-info/METADATA
koicore-1.2.0.dist-info/RECORD
koicore-1.2.0.dist-info/WHEEL
koicore-1.2.0.dist-info/metadata.json
koicore-1.2.0.dist-info/top_level.txt
